{
    "fluentMethods": true,
    "relationships": [
        {
            "relationshipType": "many-to-one",
            "relationshipName": "tag",
            "otherEntityName": "bild",
            "otherEntityField": "id"
        }
    ],
    "fields": [
        {
            "fieldName": "tag",
            "fieldType": "String"
        }
    ],
    "changelogDate": "20180126140017",
    "entityTableName": "tag",
    "dto": "mapstruct",
    "pagination": "no",
    "service": "serviceImpl",
    "jpaMetamodelFiltering": false,
    "angularJSSuffix": "mySuffix"
}